{
  "tabs": [
    {
      "id": "livingroom",
      "title": "Living Room",
      "cards": [
        {
          "id": "card1",
          "title": "Climate",
          "items": [
            {
              "type": "sensor",
              "entity_id": "sensor.sonoff_snzb_02d_temperature",
              "iconClass": "fas fa-thermometer-half",
              "name": "Temperature",
              "unit": "°C"
            },
            {
              "type": "sensor",
              "entity_id": "sensor.sonoff_snzb_02d_humidity",
              "iconClass": "fas fa-tint",
              "name": "Humidity",
              "unit": "%"
            }
          ]
        },
        {
          "id": "card2",
          "title": "Small Light",
          "items": [
            {
              "type": "control",
              "entity_id": "light.osram_light",
              "name": "Light",
              "unit": "%",
              "iconClasses": {
                "on": "fas fa-lightbulb",
                "off": "far fa-lightbulb"
              }
            }
          ]
        },
        {
          "id": "card3",
          "title": "Doors & Windows",
          "items": [
            {
              "type": "status",
              "entity_id": "binary_sensor.lumi_lumi_sensor_magnet_aq2_offnung",
              "name": "Door Entrance",
              "iconClasses": {
                "on": "fas fa-door-open",
                "off": "fas fa-door-closed"
              }
            }
          ]
        }
      ]
    },
    {
      "id": "kitchen",
      "title": "Kitchen",
      "cards": [
        {
          "id": "card1",
          "title": "Climate",
          "items": [
            {
              "type": "sensor",
              "entity_id": "sensor.tze204_s139roas_ts0601_temperaturw",
              "iconClass": "fas fa-thermometer-half",
              "name": "Temperaturw",
              "unit": "°C"
            },
            {
              "type": "sensor",
              "entity_id": "sensor.tze204_s139roas_ts0601_humidity",
              "iconClass": "fas fa-tint",
              "name": "Humidity",
              "unit": "%"
            }
          ]
        }
      ]
    }
  ]
}